slurm_sweep/__init__.py
slurm_sweep/_logging.py
slurm_sweep/cli.py
slurm_sweep/main.py
slurm_sweep/sweep_class.py
slurm_sweep/utils.py
slurm_sweep-0.2.1.dist-info/METADATA
slurm_sweep-0.2.1.dist-info/WHEEL
slurm_sweep-0.2.1.dist-info/entry_points.txt
slurm_sweep-0.2.1.dist-info/licenses/LICENSE
slurm_sweep-0.2.1.dist-info/RECORD
