Metadata-Version: 2.4
Name: slurm-sweep
Version: 0.2.1
Summary: Hyperparameter sweeps on slurm
Project-URL: Documentation, https://github.com/quadbio/slurm_sweep
Project-URL: Homepage, https://github.com/quadbio/slurm_sweep
Project-URL: Source, https://github.com/quadbio/slurm_sweep
Author: Marius Lange
Maintainer-email: Marius Lange <marius.lange@bsse.ethz.ch>
License: MIT License
License-File: LICENSE
Classifier: Programming Language :: Python :: 3 :: Only
Classifier: Programming Language :: Python :: 3.11
Classifier: Programming Language :: Python :: 3.12
Classifier: Programming Language :: Python :: 3.13
Classifier: Programming Language :: Python :: 3.14
Requires-Python: >=3.11
Requires-Dist: numpy
Requires-Dist: session-info2
Requires-Dist: simple-slurm
Requires-Dist: typer
Requires-Dist: wandb
Provides-Extra: dev
Requires-Dist: pre-commit; extra == 'dev'
Requires-Dist: twine>=4.0.2; extra == 'dev'
Provides-Extra: doc
Requires-Dist: docutils!=0.18.*,!=0.19.*,>=0.8; extra == 'doc'
Requires-Dist: ipykernel; extra == 'doc'
Requires-Dist: ipython; extra == 'doc'
Requires-Dist: myst-nb>=1.1; extra == 'doc'
Requires-Dist: pandas; extra == 'doc'
Requires-Dist: setuptools; extra == 'doc'
Requires-Dist: sphinx-autodoc-typehints; extra == 'doc'
Requires-Dist: sphinx-book-theme>=1; extra == 'doc'
Requires-Dist: sphinx-copybutton; extra == 'doc'
Requires-Dist: sphinx-tabs; extra == 'doc'
Requires-Dist: sphinx>=8.1; extra == 'doc'
Requires-Dist: sphinxcontrib-bibtex>=1; extra == 'doc'
Requires-Dist: sphinxext-opengraph; extra == 'doc'
Provides-Extra: examples
Requires-Dist: scembed; extra == 'examples'
Provides-Extra: test
Requires-Dist: coverage>=7.10; extra == 'test'
Requires-Dist: pytest; extra == 'test'
Requires-Dist: pytest-cov; extra == 'test'
